odoo/addons/web_widget_digitized_signature/README.rst
odoo/addons/web_widget_digitized_signature/__init__.py
odoo/addons/web_widget_digitized_signature/__manifest__.py
odoo/addons/web_widget_digitized_signature/i18n/ca.po
odoo/addons/web_widget_digitized_signature/i18n/de.po
odoo/addons/web_widget_digitized_signature/i18n/es.po
odoo/addons/web_widget_digitized_signature/i18n/fr.po
odoo/addons/web_widget_digitized_signature/i18n/hr.po
odoo/addons/web_widget_digitized_signature/i18n/lt.po
odoo/addons/web_widget_digitized_signature/i18n/nl_NL.po
odoo/addons/web_widget_digitized_signature/i18n/pt.po
odoo/addons/web_widget_digitized_signature/i18n/pt_BR.po
odoo/addons/web_widget_digitized_signature/i18n/sl.po
odoo/addons/web_widget_digitized_signature/i18n/web_widget_digitized_signature.pot
odoo/addons/web_widget_digitized_signature/i18n/zh_CN.po
odoo/addons/web_widget_digitized_signature/models/__init__.py
odoo/addons/web_widget_digitized_signature/models/mail_thread.py
odoo/addons/web_widget_digitized_signature/models/res_users.py
odoo/addons/web_widget_digitized_signature/readme/CONFIGURE.rst
odoo/addons/web_widget_digitized_signature/readme/CONTRIBUTORS.rst
odoo/addons/web_widget_digitized_signature/readme/CREDITS.rst
odoo/addons/web_widget_digitized_signature/readme/DESCRIPTION.rst
odoo/addons/web_widget_digitized_signature/readme/USAGE.rst
odoo/addons/web_widget_digitized_signature/static/description/icon.png
odoo/addons/web_widget_digitized_signature/static/description/index.html
odoo/addons/web_widget_digitized_signature/static/lib/jSignature/jSignatureCustom.js
odoo/addons/web_widget_digitized_signature/static/src/js/digital_sign.js
odoo/addons/web_widget_digitized_signature/static/src/xml/digital_sign.xml
odoo/addons/web_widget_digitized_signature/tests/__init__.py
odoo/addons/web_widget_digitized_signature/tests/test_signature_tracking.py
odoo/addons/web_widget_digitized_signature/views/res_users_view.xml
odoo12_addon_web_widget_digitized_signature-12.0.2.1.0.dist-info/METADATA
odoo12_addon_web_widget_digitized_signature-12.0.2.1.0.dist-info/WHEEL
odoo12_addon_web_widget_digitized_signature-12.0.2.1.0.dist-info/top_level.txt
odoo12_addon_web_widget_digitized_signature-12.0.2.1.0.dist-info/RECORD
